qualpay/error.py
qualpay/card.py
qualpay/requestor.py
qualpay/encoder.py
qualpay/gateway.py
qualpay/__init__.py
qualpay/compat.py
qualpay-1.0.1.dist-info/RECORD
qualpay-1.0.1.dist-info/top_level.txt
qualpay-1.0.1.dist-info/pbr.json
qualpay-1.0.1.dist-info/METADATA
qualpay-1.0.1.dist-info/DESCRIPTION.rst
qualpay-1.0.1.dist-info/WHEEL
qualpay-1.0.1.dist-info/metadata.json
