Metadata-Version: 2.0
Name: qualpay
Version: 1.0.1
Summary: Python bindings for Qualpay
Home-page: https://github.com/dmpayton/qualpay-python
Author: Derek Payton
Author-email: derek.payton@gmail.com
License: MIT
Keywords: payment processing qualpay
Platform: UNKNOWN
Classifier: Development Status :: 4 - Beta
Classifier: Intended Audience :: Developers
Classifier: License :: OSI Approved :: MIT License
Classifier: Programming Language :: Python
Classifier: Programming Language :: Python :: 2.7
Classifier: Programming Language :: Python :: 3.4
Classifier: Topic :: Software Development :: Libraries :: Python Modules
Requires-Dist: requests
